[
	{
		"screenshot":"https://g0v.github.io/moc-license-center/portfolio/illustration/g0.0v%E4%BF%9D%E8%AD%B7%E7%9C%BC%E7%9D%9B/tuiry",
		"name":	{
			"zh": "g0v.0v保護眼睛"
		},
		"intro": {
			"short":{
				"zh": "傳陳冠希示愛，AV版《神鬼奇航》，冏編的哥哥的女友的朋友的三叔...目前還失業找不到工作哩...難不成水果報有聽到我的心聲，尼克狂贏17分，變調情人節，遠比上Google搜尋更有效率，有人招了。"
			}
		}, 
		"authors": [
			{
				"name": "tuiry"
			},
			{
				"name": "runny"
			}
		],
		"license": ["CC-BY g0v.tw"],
		"type": ["插畫"],
		"belongs_to": ["g0v"],
		"sources": [
			{
				"size": "1920x1080",
				"format": "PSD",
				"published_at": "2013.01.01",
				"updated_at": "2013.01.01"
			}
		]
	}
]